plcsimulator/App.py
plcsimulator/BaseFieldbusModule.py
plcsimulator/Configurator.py
plcsimulator/FieldbusManager.py
plcsimulator/FieldbusMessage.py
plcsimulator/IoManager.py
plcsimulator/Listener.py
plcsimulator/MemoryManager.py
plcsimulator/ModbusModule.py
plcsimulator/__init__.py
plcsimulator/__main__.py
plcsimulator/examples/plc-simulator-conf.json
plc_simulator-0.5.0.dist-info/entry_points.txt
plc_simulator-0.5.0.dist-info/LICENSE
plc_simulator-0.5.0.dist-info/WHEEL
plc_simulator-0.5.0.dist-info/METADATA
plc_simulator-0.5.0.dist-info/RECORD
