Metadata-Version: 2.1
Name: plc-simulator
Version: 0.5.0
Summary: PLC Simulation Environment
Home-page: https://github.com/paul-breen/plc-simulator
License: Apache-2.0
Author: Paul Breen
Author-email: pbree@bas.ac.uk
Requires-Python: >=3.8,<4.0
Classifier: License :: OSI Approved :: Apache Software License
Classifier: Programming Language :: Python :: 3
Classifier: Programming Language :: Python :: 3.8
Classifier: Programming Language :: Python :: 3.9
Classifier: Programming Language :: Python :: 3.10
Classifier: Programming Language :: Python :: 3.11
Project-URL: Documentation, https://paul-breen.github.io/plc-simulator/
Project-URL: Repository, https://github.com/paul-breen/plc-simulator
